user_inputs_for_args/__init__.py
user_inputs_for_args-0.0.2.dist-info/METADATA
user_inputs_for_args-0.0.2.dist-info/WHEEL
user_inputs_for_args-0.0.2.dist-info/top_level.txt
user_inputs_for_args-0.0.2.dist-info/RECORD
