Metadata-Version: 2.1
Name: user-inputs-for-args
Version: 0.0.2
Summary: gets inputs from the user on the cmd line for params that you haven't entered programmatically
Home-page: https://gitlab.com/section.80/user_inputs_for_args
Author: Brooklyn Germa
Author-email: brooklyn.germa@gmail.com
License: UNKNOWN
Platform: UNKNOWN
Classifier: Programming Language :: Python :: 3.7
Classifier: License :: OSI Approved :: MIT License
Classifier: Operating System :: OS Independent
